antiseptic-0.2.0.dist-info/METADATA
antiseptic-0.2.0.dist-info/WHEEL
antiseptic-0.2.0.dist-info/entry_points.txt
antiseptic-0.2.0.dist-info/licenses/LICENSE.txt
antiseptic/__init__.py
antiseptic/_lowlevel.cpython-38-x86_64-linux-gnu.so
antiseptic/_lowlevel.pyi
antiseptic/assets/dictionaries/en.txt
antiseptic/assets/logo/logo-dark.svg
antiseptic/assets/logo/logo-light.svg
antiseptic-0.2.0.dist-info/RECORD
