Metadata-Version: 2.4
Name: antiseptic
Version: 0.2.0
License-File: LICENSE.txt
Summary: CI spell-checking tool
License: AGPL-3.0-only
Requires-Python: >=3.8
Project-URL: Homepage, https://github.com/clockback/antiseptic
Project-URL: Issues, https://github.com/clockback/antiseptic/issues
Project-URL: Changelog, https://github.com/clockback/antiseptic/blob/main/CHANGELOG.md
